pycc/__init__.py
pycc/eval_cc.py
pycc/evaluate.py
pycc/forward_integration.py
pycc/post_processing.py
pycc/post_processing_SymbR.py
pycc/post_processing_SymbR_backup.py
pycc/print_cc.py
pycc/process_evals_SymbR.py
pycc/simulate_NN.py
pycc/simulate_Poly.py
pycc/simulate_SymbR.py
pycc/simulate_SymbR_only_SR.py
pycc/simulate_from_evals_interp.py
pycc/simulate_manager.py
pycc/simulate_th.py
pycc/simulate_th_backup.py
pycc/train_GP.py
pycc/train_NN_hybrid.py
pycc/train_NN_hybrid_backup_1.py
pycc/train_NN_hybrid_backup_2.py
pycc/train_NN_hybrid_backup_3_trying_improve_params_fitting.py
pycc/train_NN_hybrid_backup_4with_verification_detaframe.py
pycc/train_NN_hybrid_backup_5.py
pycc/train_SparseR.py
pycc/train_SymbR.py
pycc/train_SymbReg_backup1.py
pycc/train_SymbReg_backup2_work_but_harcoded.py
pycc/train_SymbReg_backup3_working_but_fiopposite.py
pycc/train_manager.py
pycc/train_old.py
pycc/train_polynomial.py
pycc/train_polynomial_backup_old.py
pycc/train_polynomial_improved_parametric.py
pycc/train_polynomial_linear.py
pycc/train_s.py
pycc_id-0.5.5.dist-info/licenses/LICENSE
pycc_id-0.5.5.dist-info/METADATA
pycc_id-0.5.5.dist-info/WHEEL
pycc_id-0.5.5.dist-info/top_level.txt
pycc_id-0.5.5.dist-info/RECORD
